pyopl/__init__.py
pyopl/__main__.py
pyopl/genai_pricing.cp313-win_amd64.pyd
pyopl/genai_pricing.pyx
pyopl/gurobi_codegen.cp313-win_amd64.pyd
pyopl/gurobi_codegen.pyx
pyopl/pyopl_core.py
pyopl/pyopl_generative.cp313-win_amd64.pyd
pyopl/pyopl_generative.pyi
pyopl/pyopl_generative.pyx
pyopl/pyopl_ide_bootstrap.cp313-win_amd64.pyd
pyopl/pyopl_ide_bootstrap.pyx
pyopl/rag_helper.cp313-win_amd64.pyd
pyopl/rag_helper.pyx
pyopl/scipy_codegen.cp313-win_amd64.pyd
pyopl/scipy_codegen.pyx
pyopl/scipy_codegen_base.cp313-win_amd64.pyd
pyopl/scipy_codegen_base.pyx
pyopl/scipy_codegen_csc.cp313-win_amd64.pyd
pyopl/scipy_codegen_csc.pyx
pyopl/semantic_error.cp313-win_amd64.pyd
pyopl/semantic_error.pyx
pyopl/tuple_set_helper.cp313-win_amd64.pyd
pyopl/tuple_set_helper.pyx
pyopl/grammars/JSON_SCHEMA_AST.json
pyopl/grammars/PyOPL grammar.md
pyopl/grammars/PyOPL_GBNF
pyopl/icon/__init__.py
pyopl/icon/gear.png
pyopl/icon/mindset.png
pyopl/opl_models/assignment/assignment.dat
pyopl/opl_models/assignment/assignment.mod
pyopl/opl_models/assignment/assignment.txt
pyopl/opl_models/covering/covering.dat
pyopl/opl_models/covering/covering.mod
pyopl/opl_models/covering/covering.txt
pyopl/opl_models/crew_pairing/crew_pairing.dat
pyopl/opl_models/crew_pairing/crew_pairing.mod
pyopl/opl_models/crew_pairing/crew_pairing.txt
pyopl/opl_models/crew_scheduling/crew_scheduling.dat
pyopl/opl_models/crew_scheduling/crew_scheduling.mod
pyopl/opl_models/crew_scheduling/crew_scheduling.txt
pyopl/opl_models/graph_coloring/graph_coloring.dat
pyopl/opl_models/graph_coloring/graph_coloring.mod
pyopl/opl_models/graph_coloring/graph_coloring.txt
pyopl/opl_models/inventory_routing/inventory_routing.dat
pyopl/opl_models/inventory_routing/inventory_routing.mod
pyopl/opl_models/inventory_routing/inventory_routing.txt
pyopl/opl_models/jobshop/jobshop.dat
pyopl/opl_models/jobshop/jobshop.mod
pyopl/opl_models/jobshop/jobshop.txt
pyopl/opl_models/knapsack/knapsack.dat
pyopl/opl_models/knapsack/knapsack.mod
rhetor-1.1.3.dist-info/METADATA
rhetor-1.1.3.dist-info/WHEEL
rhetor-1.1.3.dist-info/top_level.txt
rhetor-1.1.3.dist-info/RECORD
